Metadata-Version: 1.0
Name: networksearch
Version: 0.1
Summary: A lib for search network overlaps
Home-page: https://github.com/HenriqueCaires/network-search
Author: Henrique Caires
Author-email: henrique@caires.net.br
License: MIT
Platform: UNKNOWN
